scame/__init__.py
scame/__main__.py
scame/__version__.py
scame/formatcheck.py
scame/reporter.py
scame/contrib/__init__.py
scame/contrib/cssccc.py
scame/tests/__init__.py
scame/tests/test_css.py
scame/tests/test_cssccc.py
scame/tests/test_javascript.py
scame/tests/test_json.py
scame/tests/test_python.py
scame/tests/test_reporter.py
scame/tests/test_restructuredtext.py
scame/tests/test_sql.py
scame/tests/test_text.py
scame/tests/test_xml.py
scame-0.5.1.dist-info/DESCRIPTION.rst
scame-0.5.1.dist-info/METADATA
scame-0.5.1.dist-info/RECORD
scame-0.5.1.dist-info/WHEEL
scame-0.5.1.dist-info/entry_points.txt
scame-0.5.1.dist-info/metadata.json
scame-0.5.1.dist-info/top_level.txt
