Metadata-Version: 2.0
Name: scame
Version: 0.5.1
Summary: A composite linter and style checker.
Home-page: https://github.com/chevah/scame
Maintainer: Adi Roiban
Maintainer-email: adi.roiban@chevah.com
License: UNKNOWN
Platform: UNKNOWN
Provides-Extra: dev
Requires-Dist: pyflakes
Provides-Extra: dev
Requires-Dist: bandit; extra == 'dev'
Requires-Dist: nose; extra == 'dev'
Requires-Dist: pycodestyle; extra == 'dev'
Requires-Dist: pylint; extra == 'dev'
